[
  {
    "name": "Innsbruckring",
    "id": "2592027600",
    "decisions": [
      {
        "markerId": "70004",
        "turn": "0",
        "forward": "1",
        "stub": "0"
      },
      {
        "markerId": "140000",
        "turn": "3",
        "forward": "0",
        "stub": "0"
      }
    ]
  },
  {
    "name": "2018 Worlds Short Lap",
    "id": "3114603308",
    "decisions": [
      {
        "markerId": "70004",
        "turn": "3",
        "forward": "1",
        "stub": "0"
      },
      {
        "markerId": "70006",
        "turn": "1",
        "forward": "1",
        "stub": "0"
      },
      {
        "markerId": "70002",
        "turn": "1",
        "forward": "1",
        "stub": "0"
      },
      {
        "markerId": "60000",
        "turn": "3",
        "forward": "1",
        "stub": "0"
      },
      {
        "markerId": "70007",
        "turn": "1",
        "forward": "1",
        "stub": "0"
      }
    ]
  },
  {
    "name": "Achterbahn",
    "id": "4009235104",
    "decisions": [
      {
        "markerId": "70004",
        "turn": "3",
        "forward": "1",
        "stub": "0"
      },
      {
        "markerId": "70006",
        "turn": "0",
        "forward": "1",
        "stub": "0"
      },
      {
        "markerId": "150000",
        "turn": "3",
        "forward": "1",
        "stub": "0"
      },
      {
        "markerId": "70001",
        "turn": "0",
        "forward": "0",
        "stub": "0"
      },
      {
        "markerId": "70007",
        "turn": "3",
        "forward": "0",
        "stub": "0"
      },
      {
        "markerId": "70005",
        "turn": "3",
        "forward": "0",
        "stub": "0"
      },
      {
        "markerId": "70000",
        "turn": "1",
        "forward": "0",
        "stub": "0"
      },
      {
        "markerId": "20000",
        "turn": "3",
        "forward": "1",
        "stub": "0"
      },
      {
        "markerId": "70002",
        "turn": "1",
        "forward": "1",
        "stub": "0"
      },
      {
        "markerId": "60000",
        "turn": "3",
        "forward": "1",
        "stub": "0"
      },
      {
        "markerId": "70007",
        "turn": "1",
        "forward": "1",
        "stub": "0"
      }
    ]
  },
  {
    "name": "Lutscher CCW",
    "id": "3801241714",
    "decisions": [
      {
        "markerId": "70004",
        "turn": "3",
        "forward": "1",
        "stub": "0"
      },
      {
        "markerId": "70006",
        "turn": "0",
        "forward": "1",
        "stub": "0"
      },
      {
        "markerId": "150000",
        "turn": "3",
        "forward": "1",
        "stub": "0"
      },
      {
        "markerId": "70001",
        "turn": "3",
        "forward": "0",
        "stub": "0"
      },
      {
        "markerId": "30000",
        "turn": "3",
        "forward": "0",
        "stub": "0"
      }
    ]
  },
  {
    "name": "Lutscher",
    "id": "156457316",
    "decisions": [
      {
        "markerId": "70004",
        "turn": "3",
        "forward": "1",
        "stub": "0"
      },
      {
        "markerId": "70006",
        "turn": "1",
        "forward": "1",
        "stub": "0"
      },
      {
        "markerId": "70002",
        "turn": "3",
        "forward": "1",
        "stub": "0"
      },
      {
        "markerId": "50000",
        "turn": "3",
        "forward": "1",
        "stub": "0"
      }
    ]
  },
  {
    "name": "Innsbruck KOM After Party",
    "id": "3649347250",
    "decisions": [
      {
        "markerId": "70004",
        "turn": "0",
        "forward": "1",
        "stub": "0"
      },
      {
        "markerId": "140000",
        "turn": "3",
        "forward": "0",
        "stub": "0"
      },
      {
        "markerId": "70004",
        "turn": "0",
        "forward": "1",
        "stub": "0"
      },
      {
        "markerId": "140000",
        "turn": "3",
        "forward": "0",
        "stub": "0"
      },
      {
        "markerId": "70004",
        "turn": "0",
        "forward": "1",
        "stub": "0"
      },
      {
        "markerId": "140000",
        "turn": "3",
        "forward": "0",
        "stub": "0"
      },
      {
        "markerId": "70004",
        "turn": "3",
        "forward": "1",
        "stub": "0"
      },
      {
        "markerId": "70006",
        "turn": "1",
        "forward": "1",
        "stub": "0"
      }
    ]
  },
  {
    "name": "InnsbruckConti",
    "id": "3101693166",
    "decisions": [
      {
        "markerId": "70005",
        "turn": "3",
        "forward": "0",
        "stub": "0"
      },
      {
        "markerId": "70000",
        "turn": "0",
        "forward": "0",
        "stub": "0"
      }
    ]
  }
]
